qlsq/__init__.py
qlsq-0.7.0.dist-info/licenses/LICENSE.txt
qlsq-0.7.0.dist-info/METADATA
qlsq-0.7.0.dist-info/WHEEL
qlsq-0.7.0.dist-info/top_level.txt
qlsq-0.7.0.dist-info/RECORD
