Metadata-Version: 2.4
Name: qlsq
Version: 0.7.0
Summary: dynamic sql generetor
Author-email: Marius Kavaliauskas <mariuskava+qlsq@gmail.com>
License-Expression: MIT
Project-URL: Homepage, https://gitlab.com/qlsq/qlsq
Project-URL: Issue Tracker, https://gitlab.com/qlsq/qlsq/-/issues
Project-URL: Source Code, https://gitlab.com/qlsq/qlsq
Keywords: sql,postgresql,sql-generator
Classifier: Programming Language :: Python :: 3
Classifier: Topic :: Software Development :: Libraries
Classifier: Topic :: Software Development :: Libraries :: Python Modules
Requires-Python: >=3.12
License-File: LICENSE.txt
Dynamic: license-file
